nefertem_inference_frictionless/__init__.py
nefertem_inference_frictionless/builder.py
nefertem_inference_frictionless/plugin.py
nefertem_inference_frictionless-2.0.2.dist-info/METADATA
nefertem_inference_frictionless-2.0.2.dist-info/WHEEL
nefertem_inference_frictionless-2.0.2.dist-info/top_level.txt
nefertem_inference_frictionless-2.0.2.dist-info/RECORD
